Topsis_Sanjoli_102003425/Sanjoli_102003425.py
Topsis_Sanjoli_102003425-0.5.dist-info/Licence
Topsis_Sanjoli_102003425-0.5.dist-info/METADATA
Topsis_Sanjoli_102003425-0.5.dist-info/WHEEL
Topsis_Sanjoli_102003425-0.5.dist-info/entry_points.txt
Topsis_Sanjoli_102003425-0.5.dist-info/top_level.txt
Topsis_Sanjoli_102003425-0.5.dist-info/RECORD
