Metadata-Version: 2.1
Name: Topsis-Sanjoli-102003425
Version: 0.5
Summary: This is a topsis package of version 0.5
Home-page: UNKNOWN
Author: Sanjoli Agarwal
Author-email: sagarwal_be20@thapar.edu
License: UNKNOWN
Platform: UNKNOWN
License-File: Licence
Requires-Dist: pandas
